benchmanage/__init__.py
benchmanage/app.py
benchmanage-0.1.1.dist-info/METADATA
benchmanage-0.1.1.dist-info/WHEEL
benchmanage-0.1.1.dist-info/entry_points.txt
benchmanage-0.1.1.dist-info/top_level.txt
benchmanage-0.1.1.dist-info/RECORD
